wrench_build/__init__.py
wrench_build/lib.py
wrench_build/wr.py
wrench_build/wrb.py
wrench_build-0.1.9.dist-info/METADATA
wrench_build-0.1.9.dist-info/WHEEL
wrench_build-0.1.9.dist-info/entry_points.txt
wrench_build-0.1.9.dist-info/licenses/LICENSE
wrench_build-0.1.9.dist-info/RECORD
